rdframe/__init__.py
rdframe/cql_sparql_reference.py
rdframe/grammar/__init__.py
rdframe/grammar/readme.md
rdframe/grammar/sparql_grammar.py
rdframe/x_to_sparql/__init__.py
rdframe/x_to_sparql/cql2sparql.py
rdframe/x_to_sparql/shacl2sparql.py
rdframe-0.1.1.dist-info/METADATA
rdframe-0.1.1.dist-info/WHEEL
rdframe-0.1.1.dist-info/RECORD
