Metadata-Version: 2.1
Name: rdframe
Version: 0.1.1
Summary: 
Author: david
Author-email: dcchabgood@gmail.com
Requires-Python: >=3.11,<4.0
Classifier: Programming Language :: Python :: 3
Classifier: Programming Language :: Python :: 3.11
Classifier: Programming Language :: Python :: 3.12
Requires-Dist: pydantic (>=2.5.2,<3.0.0)
Requires-Dist: pyld (>=2.0.3,<3.0.0)
Requires-Dist: rdflib (>=7.0.0,<8.0.0)
Requires-Dist: shapely (>=2.0.2,<3.0.0)
